deep_nest/__init__.py
deep_nest/deep_nest.py
deep_nest-0.14.dist-info/DESCRIPTION.rst
deep_nest-0.14.dist-info/METADATA
deep_nest-0.14.dist-info/RECORD
deep_nest-0.14.dist-info/WHEEL
deep_nest-0.14.dist-info/metadata.json
deep_nest-0.14.dist-info/top_level.txt
