Metadata-Version: 2.0
Name: deep-nest
Version: 0.14
Summary: A sane approach to arbitrarily nested dictionaries (*cough* nested JSON *cough*)
Home-page: https://github.com/lruhlen/deep_nest
Author: L. Ruhlen
Author-email: ruhlen@gmail.com
License: MIT
Platform: UNKNOWN
